mirtime/__init__.py
mirtime/__main__.py
mirtime/cli.py
mirtime/clustering.py
mirtime/correlation.py
mirtime/firstfilter.py
mirtime/gplearning.py
mirtime/run_DESeq.R
mirtime/run_limma_with_expression_table.R
mirtime/util.py
mirtime-0.1.0.dist-info/DESCRIPTION.rst
mirtime-0.1.0.dist-info/METADATA
mirtime-0.1.0.dist-info/RECORD
mirtime-0.1.0.dist-info/WHEEL
mirtime-0.1.0.dist-info/entry_points.txt
mirtime-0.1.0.dist-info/metadata.json
mirtime-0.1.0.dist-info/top_level.txt
